Code/Register_File/register_file.v
module registers (
    input wire clk,
    input wire write_en,
    input wire reset,
    input wire [7:0] in_bus,
    output reg [7:0] A
);
    always @(posedge clk) begin
        if(reset) begin
            A <= 8'b00000000;
        end else if(write_en) begin
            A <= in_bus;
        end
    end
endmodule

module four_in_mux (
    input wire [7:0] a,
    input wire [7:0] b,
    input wire [7:0] c,
    input wire [7:0] d,
    input wire [1:0] sel,
    output reg [7:0] y
);
    always @(*) begin
        case (sel)
            2'b00 : y = a;
            2'b01 : y = b;
            2'b10 : y = c;
            2'b11 : y = d;
            default: y = 8'b00000000;
        endcase
    end
endmodule

module register_file (
    input wire clk,
    input wire reset,
    input wire write_en,
    input wire [1:0] write_sel, port_a_sel, port_b_sel,
    input wire [7:0] input_data,
    output wire [7:0] port_a_data, port_b_data
);
    wire [7:0] reg0_out, reg1_out, reg2_out, reg3_out;

    registers R0 (
        .clk(clk),
        .write_en(write_en & (write_sel == 2'b00)),
        .reset(reset),
        .in_bus(input_data),
        .A(reg0_out)
    );

    registers R1 (
        .clk(clk),
        .write_en(write_en & (write_sel == 2'b01)),
        .reset(reset),
        .in_bus(input_data),
        .A(reg1_out)
    );

    registers R2 (
        .clk(clk),
        .write_en(write_en & (write_sel == 2'b10)),
        .reset(reset),
        .in_bus(input_data),
        .A(reg2_out)
    );

    registers R3 (
        .clk(clk),
        .write_en(write_en & (write_sel == 2'b11)),
        .reset(reset),
        .in_bus(input_data),
        .A(reg3_out)
    );

    four_in_mux MUX_A (
        .a(reg0_out),
        .b(reg1_out),
        .c(reg2_out),
        .d(reg3_out),
        .sel(port_a_sel),
        .y(port_a_data)
    );

    four_in_mux MUX_B (
        .a(reg0_out),
        .b(reg1_out),
        .c(reg2_out),
        .d(reg3_out),
        .sel(port_b_sel),
        .y(port_b_data)
    );
endmodule

// ========== CORRECTED TESTBENCH ==========

`timescale 1ns / 1ps

module tb_register_file;

    // Inputs
    reg clk;
    reg reset;
    reg write_en;
    reg [1:0] write_sel;
    reg [1:0] port_a_sel;
    reg [1:0] port_b_sel;
    reg [7:0] input_data;
    
    // Outputs
    wire [7:0] port_a_data;
    wire [7:0] port_b_data;
    
    // Instantiate the Unit Under Test (UUT)
    register_file uut (
        .clk(clk),
        .reset(reset),
        .write_en(write_en),
        .write_sel(write_sel),
        .port_a_sel(port_a_sel),
        .port_b_sel(port_b_sel),
        .input_data(input_data),
        .port_a_data(port_a_data),
        .port_b_data(port_b_data)
    );
    
    // Clock generation
    initial begin
        clk = 0;
        forever #5 clk = ~clk;
    end
    
    // Test stimulus
    initial begin
        // Initialize inputs
        reset = 0;
        write_en = 0;
        write_sel = 2'b00;
        port_a_sel = 2'b00;
        port_b_sel = 2'b00;
        input_data = 8'h00;
        
        // VCD dump for waveform viewing
        $dumpfile("register_file_tb.vcd");
        $dumpvars(0, tb_register_file);
        
        $display("===== Register File Test =====\n");
        
        // Test 1: Reset all registers
        $display("Test 1: Reset Test");
        reset = 1;
        #20;
        reset = 0;
        #10;
        port_a_sel = 2'b00; port_b_sel = 2'b01; #10;
        $display("After reset - R0: %h, R1: %h", port_a_data, port_b_data);
        port_a_sel = 2'b10; port_b_sel = 2'b11; #10;
        $display("After reset - R2: %h, R3: %h", port_a_data, port_b_data);
        
        // Test 2: Write to individual registers
        $display("\nTest 2: Write to Individual Registers");
        write_en = 1;
        
        write_sel = 2'b00; input_data = 8'hAA; #10;
        port_a_sel = 2'b00; #1;
        $display("Write %h to R0, Read R0: %h %s", 8'hAA, port_a_data, 
                 (port_a_data === 8'hAA) ? "PASS" : "FAIL");
        
        write_sel = 2'b01; input_data = 8'hBB; #10;
        port_a_sel = 2'b01; #1;
        $display("Write %h to R1, Read R1: %h %s", 8'hBB, port_a_data,
                 (port_a_data === 8'hBB) ? "PASS" : "FAIL");
        
        write_sel = 2'b10; input_data = 8'hCC; #10;
        port_a_sel = 2'b10; #1;
        $display("Write %h to R2, Read R2: %h %s", 8'hCC, port_a_data,
                 (port_a_data === 8'hCC) ? "PASS" : "FAIL");
        
        write_sel = 2'b11; input_data = 8'hDD; #10;
        port_a_sel = 2'b11; #1;
        $display("Write %h to R3, Read R3: %h %s", 8'hDD, port_a_data,
                 (port_a_data === 8'hDD) ? "PASS" : "FAIL");
        
        // Test 3: Read all registers via Port A
        $display("\nTest 3: Read All Registers via Port A");
        write_en = 0;
        port_a_sel = 2'b00; #1; $display("Port A - R0: %h", port_a_data);
        port_a_sel = 2'b01; #1; $display("Port A - R1: %h", port_a_data);
        port_a_sel = 2'b10; #1; $display("Port A - R2: %h", port_a_data);
        port_a_sel = 2'b11; #1; $display("Port A - R3: %h", port_a_data);
        
        // Test 4: Read all registers via Port B
        $display("\nTest 4: Read All Registers via Port B");
        port_b_sel = 2'b00; #1; $display("Port B - R0: %h", port_b_data);
        port_b_sel = 2'b01; #1; $display("Port B - R1: %h", port_b_data);
        port_b_sel = 2'b10; #1; $display("Port B - R2: %h", port_b_data);
        port_b_sel = 2'b11; #1; $display("Port B - R3: %h", port_b_data);
        
        // Test 5: Simultaneous dual-port read
        $display("\nTest 5: Simultaneous Dual-Port Read");
        port_a_sel = 2'b00; port_b_sel = 2'b01; #1;
        $display("Read R0 and R1 simultaneously: Port_A=%h, Port_B=%h", port_a_data, port_b_data);
        
        port_a_sel = 2'b10; port_b_sel = 2'b11; #1;
        $display("Read R2 and R3 simultaneously: Port_A=%h, Port_B=%h", port_a_data, port_b_data);
        
        port_a_sel = 2'b00; port_b_sel = 2'b11; #1;
        $display("Read R0 and R3 simultaneously: Port_A=%h, Port_B=%h", port_a_data, port_b_data);
        
        // Test 6: Write disabled (write_en = 0)
        $display("\nTest 6: Write Disable Test");
        write_en = 0;
        write_sel = 2'b00;
        input_data = 8'hFF;
        #10;
        port_a_sel = 2'b00; #1;
        $display("Attempt write %h to R0 with write_en=0, R0 remains: %h %s", 
                 8'hFF, port_a_data, (port_a_data === 8'hAA) ? "PASS" : "FAIL");
        
        // Test 7: Overwrite register
        $display("\nTest 7: Overwrite Test");
        write_en = 1;
        write_sel = 2'b00;
        input_data = 8'h11;
        #10;
        port_a_sel = 2'b00; #1;
        $display("Overwrite R0 with %h: %h %s", 8'h11, port_a_data,
                 (port_a_data === 8'h11) ? "PASS" : "FAIL");
        
        // Test 8: Write to one register while reading others
        $display("\nTest 8: Write While Reading");
        write_sel = 2'b10;
        input_data = 8'h99;
        port_a_sel = 2'b01;  // Reading R1
        port_b_sel = 2'b11;  // Reading R3
        #10;
        $display("Writing to R2, Reading R1=%h, R3=%h (should be unaffected)", 
                 port_a_data, port_b_data);
        port_a_sel = 2'b10; #1;
        $display("Now read R2: %h %s", port_a_data, (port_a_data === 8'h99) ? "PASS" : "FAIL");
        
        // Test 9: Sequential writes
        $display("\nTest 9: Sequential Writes to All Registers");
        write_en = 1;
        write_sel = 2'b00; input_data = 8'h10; #10;
        write_sel = 2'b01; input_data = 8'h20; #10;
        write_sel = 2'b10; input_data = 8'h30; #10;
        write_sel = 2'b11; input_data = 8'h40; #10;
        
        write_en = 0;
        port_a_sel = 2'b00; #1; $display("R0: %h (expected 10) %s", port_a_data, (port_a_data === 8'h10) ? "PASS" : "FAIL");
        port_a_sel = 2'b01; #1; $display("R1: %h (expected 20) %s", port_a_data, (port_a_data === 8'h20) ? "PASS" : "FAIL");
        port_a_sel = 2'b10; #1; $display("R2: %h (expected 30) %s", port_a_data, (port_a_data === 8'h30) ? "PASS" : "FAIL");
        port_a_sel = 2'b11; #1; $display("R3: %h (expected 40) %s", port_a_data, (port_a_data === 8'h40) ? "PASS" : "FAIL");
        
        // Test 10: Reset while holding data - CORRECTED
        $display("\nTest 10: Reset After Writing");
        write_en = 1;
        write_sel = 2'b00; input_data = 8'hEE; #10;
        write_sel = 2'b01; input_data = 8'hEF; #10;
        
        // CRITICAL FIX: Disable write_en BEFORE asserting reset
        write_en = 0;
        #5;  // Small delay to ensure write_en is low
        
        reset = 1; #20; reset = 0; #10;
        
        // Now check that all registers are reset to 0
        port_a_sel = 2'b00; port_b_sel = 2'b01; #1;
        $display("After reset: R0=%h, R1=%h %s", port_a_data, port_b_data,
                 (port_a_data === 8'h00 && port_b_data === 8'h00) ? "PASS" : "FAIL");
        port_a_sel = 2'b10; port_b_sel = 2'b11; #1;
        $display("After reset: R2=%h, R3=%h %s", port_a_data, port_b_data,
                 (port_a_data === 8'h00 && port_b_data === 8'h00) ? "PASS" : "FAIL");
        
        // Test 11: Reset priority over write
        $display("\nTest 11: Reset Priority Test");
        write_en = 1;
        write_sel = 2'b00;
        input_data = 8'hAB;
        reset = 1;  // Assert reset while trying to write
        #10;
        reset = 0;
        write_en = 0;
        #10;
        port_a_sel = 2'b00; #1;
        $display("Reset while writing: R0=%h (expected 00) %s", port_a_data,
                 (port_a_data === 8'h00) ? "PASS" : "FAIL");
        
        $display("\n===== Test Complete =====");
        #50;
        $finish;
    end
    
    // Monitor
    initial begin
        $monitor("Time=%0t | clk=%b rst=%b we=%b | wsel=%b data_in=%h | pa_sel=%b pa_data=%h | pb_sel=%b pb_data=%h",
                 $time, clk, reset, write_en, write_sel, input_data, 
                 port_a_sel, port_a_data, port_b_sel, port_b_data);
    end

endmodule

Code/Register_File/register_file_tb.vcd
$date
	Sat Nov 22 21:46:40 2025
$end
$version
	Icarus Verilog
$end
$timescale
	1ps
$end
$scope module tb_register_file $end
$var wire 8 ! port_b_data [7:0] $end
$var wire 8 " port_a_data [7:0] $end
$var reg 1 # clk $end
$var reg 8 $ input_data [7:0] $end
$var reg 2 % port_a_sel [1:0] $end
$var reg 2 & port_b_sel [1:0] $end
$var reg 1 ' reset $end
$var reg 1 ( write_en $end
$var reg 2 ) write_sel [1:0] $end
$scope module uut $end
$var wire 1 # clk $end
$var wire 8 * input_data [7:0] $end
$var wire 2 + port_a_sel [1:0] $end
$var wire 2 , port_b_sel [1:0] $end
$var wire 1 ' reset $end
$var wire 1 ( write_en $end
$var wire 2 - write_sel [1:0] $end
$var wire 8 . reg3_out [7:0] $end
$var wire 8 / reg2_out [7:0] $end
$var wire 8 0 reg1_out [7:0] $end
$var wire 8 1 reg0_out [7:0] $end
$var wire 8 2 port_b_data [7:0] $end
$var wire 8 3 port_a_data [7:0] $end
$scope module MUX_A $end
$var wire 2 4 sel [1:0] $end
$var wire 8 5 d [7:0] $end
$var wire 8 6 c [7:0] $end
$var wire 8 7 b [7:0] $end
$var wire 8 8 a [7:0] $end
$var reg 8 9 y [7:0] $end
$upscope $end
$scope module MUX_B $end
$var wire 2 : sel [1:0] $end
$var wire 8 ; d [7:0] $end
$var wire 8 < c [7:0] $end
$var wire 8 = b [7:0] $end
$var wire 8 > a [7:0] $end
$var reg 8 ? y [7:0] $end
$upscope $end
$scope module R0 $end
$var wire 1 # clk $end
$var wire 8 @ in_bus [7:0] $end
$var wire 1 ' reset $end
$var wire 1 A write_en $end
$var reg 8 B A [7:0] $end
$upscope $end
$scope module R1 $end
$var wire 1 # clk $end
$var wire 8 C in_bus [7:0] $end
$var wire 1 ' reset $end
$var wire 1 D write_en $end
$var reg 8 E A [7:0] $end
$upscope $end
$scope module R2 $end
$var wire 1 # clk $end
$var wire 8 F in_bus [7:0] $end
$var wire 1 ' reset $end
$var wire 1 G write_en $end
$var reg 8 H A [7:0] $end
$upscope $end
$scope module R3 $end
$var wire 1 # clk $end
$var wire 8 I in_bus [7:0] $end
$var wire 1 ' reset $end
$var wire 1 J write_en $end
$var reg 8 K A [7:0] $end
$upscope $end
$upscope $end
$upscope $end
$enddefinitions $end
#0
$dumpvars
bx K
0J
b0 I
bx H
0G
b0 F
bx E
0D
b0 C
bx B
0A
b0 @
bx ?
bx >
bx =
bx <
bx ;
b0 :
bx 9
bx 8
bx 7
bx 6
bx 5
b0 4
bx 3
bx 2
bx 1
bx 0
bx /
bx .
b0 -
b0 ,
b0 +
b0 *
b0 )
0(
1'
b0 &
b0 %
b0 $
0#
bx "
bx !
$end
#5000
b0 "
b0 3
b0 9
b0 !
b0 2
b0 ?
b0 1
b0 8
b0 >
b0 B
b0 0
b0 7
b0 =
b0 E
b0 /
b0 6
b0 <
b0 H
b0 .
b0 5
b0 ;
b0 K
1#
#10000
0#
#15000
1#
#20000
0#
0'
#25000
1#
#30000
0#
b1 &
b1 ,
b1 :
#35000
1#
#40000
0#
b11 &
b11 ,
b11 :
b10 %
b10 +
b10 4
#45000
1#
#50000
1A
0#
b10101010 $
b10101010 *
b10101010 @
b10101010 C
b10101010 F
b10101010 I
1(
#55000
b10101010 1
b10101010 8
b10101010 >
b10101010 B
1#
#60000
b10101010 "
b10101010 3
b10101010 9
0#
b0 %
b0 +
b0 4
#61000
0A
1D
b10111011 $
b10111011 *
b10111011 @
b10111011 C
b10111011 F
b10111011 I
b1 )
b1 -
#65000
b10111011 0
b10111011 7
b10111011 =
b10111011 E
1#
#70000
0#
#71000
b10111011 "
b10111011 3
b10111011 9
b1 %
b1 +
b1 4
#72000
0D
1G
b11001100 $
b11001100 *
b11001100 @
b11001100 C
b11001100 F
b11001100 I
b10 )
b10 -
#75000
b11001100 /
b11001100 6
b11001100 <
b11001100 H
1#
#80000
0#
#82000
b11001100 "
b11001100 3
b11001100 9
b10 %
b10 +
b10 4
#83000
0G
1J
b11011101 $
b11011101 *
b11011101 @
b11011101 C
b11011101 F
b11011101 I
b11 )
b11 -
#85000
b11011101 !
b11011101 2
b11011101 ?
b11011101 .
b11011101 5
b11011101 ;
b11011101 K
1#
#90000
0#
#93000
b11011101 "
b11011101 3
b11011101 9
b11 %
b11 +
b11 4
#94000
b10101010 "
b10101010 3
b10101010 9
0J
b0 %
b0 +
b0 4
0(
#95000
b10111011 "
b10111011 3
b10111011 9
b1 %
b1 +
b1 4
1#
#96000
b11001100 "
b11001100 3
b11001100 9
b10 %
b10 +
b10 4
#97000
b11011101 "
b11011101 3
b11011101 9
b11 %
b11 +
b11 4
#98000
b10101010 !
b10101010 2
b10101010 ?
b0 &
b0 ,
b0 :
#99000
b10111011 !
b10111011 2
b10111011 ?
b1 &
b1 ,
b1 :
#100000
b11001100 !
b11001100 2
b11001100 ?
b10 &
b10 ,
b10 :
0#
#101000
b11011101 !
b11011101 2
b11011101 ?
b11 &
b11 ,
b11 :
#102000
b10111011 !
b10111011 2
b10111011 ?
b10101010 "
b10101010 3
b10101010 9
b1 &
b1 ,
b1 :
b0 %
b0 +
b0 4
#103000
b11011101 !
b11011101 2
b11011101 ?
b11001100 "
b11001100 3
b11001100 9
b11 &
b11 ,
b11 :
b10 %
b10 +
b10 4
#104000
b10101010 "
b10101010 3
b10101010 9
b0 %
b0 +
b0 4
#105000
b11111111 $
b11111111 *
b11111111 @
b11111111 C
b11111111 F
b11111111 I
b0 )
b0 -
1#
#110000
0#
#115000
1#
#116000
1A
b10001 $
b10001 *
b10001 @
b10001 C
b10001 F
b10001 I
1(
#120000
0#
#125000
b10001 "
b10001 3
b10001 9
b10001 1
b10001 8
b10001 >
b10001 B
1#
#127000
b10111011 "
b10111011 3
b10111011 9
0A
1G
b1 %
b1 +
b1 4
b10011001 $
b10011001 *
b10011001 @
b10011001 C
b10011001 F
b10011001 I
b10 )
b10 -
#130000
0#
#135000
b10011001 /
b10011001 6
b10011001 <
b10011001 H
1#
#137000
b10011001 "
b10011001 3
b10011001 9
b10 %
b10 +
b10 4
#138000
1A
0G
b10000 $
b10000 *
b10000 @
b10000 C
b10000 F
b10000 I
b0 )
b0 -
#140000
0#
#145000
b10000 1
b10000 8
b10000 >
b10000 B
1#
#148000
0A
1D
b100000 $
b100000 *
b100000 @
b100000 C
b100000 F
b100000 I
b1 )
b1 -
#150000
0#
#155000
b100000 0
b100000 7
b100000 =
b100000 E
1#
#158000
0D
1G
b110000 $
b110000 *
b110000 @
b110000 C
b110000 F
b110000 I
b10 )
b10 -
#160000
0#
#165000
b110000 "
b110000 3
b110000 9
b110000 /
b110000 6
b110000 <
b110000 H
1#
#168000
0G
1J
b1000000 $
b1000000 *
b1000000 @
b1000000 C
b1000000 F
b1000000 I
b11 )
b11 -
#170000
0#
#175000
b1000000 !
b1000000 2
b1000000 ?
b1000000 .
b1000000 5
b1000000 ;
b1000000 K
1#
#178000
b10000 "
b10000 3
b10000 9
0J
b0 %
b0 +
b0 4
0(
#179000
b100000 "
b100000 3
b100000 9
b1 %
b1 +
b1 4
#180000
b110000 "
b110000 3
b110000 9
b10 %
b10 +
b10 4
0#
#181000
b1000000 "
b1000000 3
b1000000 9
b11 %
b11 +
b11 4
#182000
1A
b11101110 $
b11101110 *
b11101110 @
b11101110 C
b11101110 F
b11101110 I
b0 )
b0 -
1(
#185000
b11101110 1
b11101110 8
b11101110 >
b11101110 B
1#
#190000
0#
#192000
0A
1D
b11101111 $
b11101111 *
b11101111 @
b11101111 C
b11101111 F
b11101111 I
b1 )
b1 -
#195000
b11101111 0
b11101111 7
b11101111 =
b11101111 E
1#
#200000
0#
#202000
0D
0(
#205000
1#
#207000
1'
#210000
0#
#215000
b0 "
b0 3
b0 9
b0 !
b0 2
b0 ?
b0 .
b0 5
b0 ;
b0 K
b0 /
b0 6
b0 <
b0 H
b0 0
b0 7
b0 =
b0 E
b0 1
b0 8
b0 >
b0 B
1#
#220000
0#
#225000
1#
#227000
0'
#230000
0#
#235000
1#
#237000
b1 &
b1 ,
b1 :
b0 %
b0 +
b0 4
#238000
b11 &
b11 ,
b11 :
b10 %
b10 +
b10 4
#239000
1A
1'
b10101011 $
b10101011 *
b10101011 @
b10101011 C
b10101011 F
b10101011 I
b0 )
b0 -
1(
#240000
0#
#245000
1#
#249000
0A
0(
0'
#250000
0#
#255000
1#
#259000
b0 %
b0 +
b0 4
