Code/Code_Memory/code_memory.v
module code_memory (
    input wire [15:0] data_in,
    input wire [5:0] write_select,
    input wire [5:0] read_select,
    input wire select,
    output wire [15:0] data_out
);
    reg [15:0] memory_array [0:63];
    integer i;
    initial begin
        for (i = 0; i < 64; i = i + 1)
        memory_array[i] = 16'b0;
    end

    always @(*) begin
        if (select) begin
            memory_array[write_select] = data_in;
        end
    end

    assign data_out = memory_array[read_select];
endmodule


`timescale 1ns / 1ps

module tb_code_memory;

    // Inputs
    reg [15:0] data_in;
    reg [5:0] write_select;
    reg [5:0] read_select;
    reg select;
    
    // Output
    wire [15:0] data_out;
    
    // Instantiate the Unit Under Test (UUT)
    code_memory uut (
        .data_in(data_in),
        .write_select(write_select),
        .read_select(read_select),
        .select(select),
        .data_out(data_out)
    );
    
    // Test variables
    integer i;
    integer errors;
    
    initial begin
        // Initialize inputs
        data_in = 16'h0000;
        write_select = 6'b0;
        read_select = 6'b0;
        select = 0;
        errors = 0;
        
        // VCD dump for waveform viewing
        $dumpfile("code_memory_tb.vcd");
        $dumpvars(0, tb_code_memory);
        
        $display("===== Code Memory Test =====\n");
        
        // Test 1: Verify initial memory state (all zeros)
        $display("Test 1: Initial Memory State");
        select = 0;
        for (i = 0; i < 64; i = i + 1) begin
            read_select = i;
            #10;
            if (data_out !== 16'h0000) begin
                $display("ERROR: Memory[%0d] = %h, expected 0000", i, data_out);
                errors = errors + 1;
            end
        end
        if (errors == 0)
            $display("PASS: All memory locations initialized to 0\n");
        else
            $display("FAIL: %0d memory locations not initialized correctly\n", errors);
        
        // Test 2: Write to specific locations and read back
        $display("Test 2: Write and Read Operations");
        select = 1;
        
        // Write to address 0
        write_select = 6'd0;
        data_in = 16'hAAAA;
        #10;
        select = 0;
        read_select = 6'd0;
        #10;
        $display("Write %h to addr %0d, Read back: %h %s", 
                 16'hAAAA, 6'd0, data_out, (data_out === 16'hAAAA) ? "PASS" : "FAIL");
        
        // Write to address 31
        select = 1;
        write_select = 6'd31;
        data_in = 16'h5555;
        #10;
        select = 0;
        read_select = 6'd31;
        #10;
        $display("Write %h to addr %0d, Read back: %h %s", 
                 16'h5555, 6'd31, data_out, (data_out === 16'h5555) ? "PASS" : "FAIL");
        
        // Write to address 63 (last location)
        select = 1;
        write_select = 6'd63;
        data_in = 16'hFFFF;
        #10;
        select = 0;
        read_select = 6'd63;
        #10;
        $display("Write %h to addr %0d, Read back: %h %s", 
                 16'hFFFF, 6'd63, data_out, (data_out === 16'hFFFF) ? "PASS" : "FAIL");
        
        // Test 3: Sequential write to all locations
        $display("\nTest 3: Sequential Write to All Locations");
        select = 1;
        for (i = 0; i < 64; i = i + 1) begin
            write_select = i;
            data_in = 16'h1000 + i;  // Write unique pattern to each location
            #10;
        end
        
        // Read back and verify
        select = 0;
        errors = 0;
        for (i = 0; i < 64; i = i + 1) begin
            read_select = i;
            #10;
            if (data_out !== (16'h1000 + i)) begin
                $display("ERROR: Memory[%0d] = %h, expected %h", i, data_out, 16'h1000 + i);
                errors = errors + 1;
            end
        end
        if (errors == 0)
            $display("PASS: All 64 locations written and verified correctly");
        else
            $display("FAIL: %0d locations have incorrect data", errors);
        
        // Test 4: Overwrite existing data
        $display("\nTest 4: Overwrite Test");
        select = 1;
        write_select = 6'd10;
        data_in = 16'hDEAD;
        #10;
        select = 0;
        read_select = 6'd10;
        #10;
        $display("First write to addr 10: %h", data_out);
        
        select = 1;
        write_select = 6'd10;
        data_in = 16'hBEEF;
        #10;
        select = 0;
        read_select = 6'd10;
        #10;
        $display("Overwrite addr 10: %h %s", 
                 data_out, (data_out === 16'hBEEF) ? "PASS" : "FAIL");
        
        // Test 5: Write disabled (select = 0)
        $display("\nTest 5: Write Disable Test");
        select = 0;
        read_select = 6'd20;
        #10;
        $display("Current value at addr 20: %h", data_out);
        
        select = 0;  // Write disabled
        write_select = 6'd20;
        data_in = 16'hCCCC;
        #10;
        read_select = 6'd20;
        #10;
        $display("After write attempt with select=0: %h %s", 
                 data_out, (data_out !== 16'hCCCC) ? "PASS (no write)" : "FAIL (wrote despite select=0)");
        
        // Test 6: Random access pattern
        $display("\nTest 6: Random Access Pattern");
        select = 1;
        write_select = 6'd5;  data_in = 16'h1111; #10;
        write_select = 6'd50; data_in = 16'h2222; #10;
        write_select = 6'd15; data_in = 16'h3333; #10;
        write_select = 6'd40; data_in = 16'h4444; #10;
        
        select = 0;
        read_select = 6'd5;  #10; $display("Read addr 5:  %h (expected 1111) %s", data_out, (data_out === 16'h1111) ? "PASS" : "FAIL");
        read_select = 6'd50; #10; $display("Read addr 50: %h (expected 2222) %s", data_out, (data_out === 16'h2222) ? "PASS" : "FAIL");
        read_select = 6'd15; #10; $display("Read addr 15: %h (expected 3333) %s", data_out, (data_out === 16'h3333) ? "PASS" : "FAIL");
        read_select = 6'd40; #10; $display("Read addr 40: %h (expected 4444) %s", data_out, (data_out === 16'h4444) ? "PASS" : "FAIL");
        
        // Test 7: Boundary conditions
        $display("\nTest 7: Boundary Address Test");
        select = 1;
        write_select = 6'd0;  data_in = 16'hA0A0; #10;
        write_select = 6'd63; data_in = 16'hB0B0; #10;
        
        select = 0;
        read_select = 6'd0;  #10; $display("Read addr 0 (min):  %h %s", data_out, (data_out === 16'hA0A0) ? "PASS" : "FAIL");
        read_select = 6'd63; #10; $display("Read addr 63 (max): %h %s", data_out, (data_out === 16'hB0B0) ? "PASS" : "FAIL");
        
        // Test 8: Simultaneous read and write to different addresses
        $display("\nTest 8: Simultaneous Read/Write Different Addresses");
        select = 1;
        write_select = 6'd25;
        data_in = 16'h9999;
        read_select = 6'd30;  // Reading different address while writing
        #10;
        $display("Reading addr 30 while writing to addr 25: %h", data_out);
        read_select = 6'd25;
        #10;
        $display("Verify write to addr 25: %h %s", data_out, (data_out === 16'h9999) ? "PASS" : "FAIL");
        
        $display("\n===== Test Complete =====");
        #20;
        $finish;
    end
    
    // Monitor for debugging
    initial begin
        $monitor("Time=%0t | select=%b | write_sel=%0d | read_sel=%0d | data_in=%h | data_out=%h",
                 $time, select, write_select, read_select, data_in, data_out);
    end

endmodule

Code/Code_Memory/code_memory_tb.vcd
$date
	Sat Nov 22 21:36:33 2025
$end
$version
	Icarus Verilog
$end
$timescale
	1ps
$end
$scope module tb_code_memory $end
$var wire 16 ! data_out [15:0] $end
$var reg 16 " data_in [15:0] $end
$var reg 6 # read_select [5:0] $end
$var reg 1 $ select $end
$var reg 6 % write_select [5:0] $end
$var integer 32 & errors [31:0] $end
$var integer 32 ' i [31:0] $end
$scope module uut $end
$var wire 16 ( data_in [15:0] $end
$var wire 16 ) data_out [15:0] $end
$var wire 6 * read_select [5:0] $end
$var wire 1 $ select $end
$var wire 6 + write_select [5:0] $end
$var integer 32 , i [31:0] $end
$upscope $end
$upscope $end
$enddefinitions $end
#0
$dumpvars
b1000000 ,
b0 +
b0 *
b0 )
b0 (
b0 '
b0 &
b0 %
0$
b0 #
b0 "
b0 !
$end
#10000
b1 #
b1 *
b1 '
#20000
b10 #
b10 *
b10 '
#30000
b11 #
b11 *
b11 '
#40000
b100 #
b100 *
b100 '
#50000
b101 #
b101 *
b101 '
#60000
b110 #
b110 *
b110 '
#70000
b111 #
b111 *
b111 '
#80000
b1000 #
b1000 *
b1000 '
#90000
b1001 #
b1001 *
b1001 '
#100000
b1010 #
b1010 *
b1010 '
#110000
b1011 #
b1011 *
b1011 '
#120000
b1100 #
b1100 *
b1100 '
#130000
b1101 #
b1101 *
b1101 '
#140000
b1110 #
b1110 *
b1110 '
#150000
b1111 #
b1111 *
b1111 '
#160000
b10000 #
b10000 *
b10000 '
#170000
b10001 #
b10001 *
b10001 '
#180000
b10010 #
b10010 *
b10010 '
#190000
b10011 #
b10011 *
b10011 '
#200000
b10100 #
b10100 *
b10100 '
#210000
b10101 #
b10101 *
b10101 '
#220000
b10110 #
b10110 *
b10110 '
#230000
b10111 #
b10111 *
b10111 '
#240000
b11000 #
b11000 *
b11000 '
#250000
b11001 #
b11001 *
b11001 '
#260000
b11010 #
b11010 *
b11010 '
#270000
b11011 #
b11011 *
b11011 '
#280000
b11100 #
b11100 *
b11100 '
#290000
b11101 #
b11101 *
b11101 '
#300000
b11110 #
b11110 *
b11110 '
#310000
b11111 #
b11111 *
b11111 '
#320000
b100000 #
b100000 *
b100000 '
#330000
b100001 #
b100001 *
b100001 '
#340000
b100010 #
b100010 *
b100010 '
#350000
b100011 #
b100011 *
b100011 '
#360000
b100100 #
b100100 *
b100100 '
#370000
b100101 #
b100101 *
b100101 '
#380000
b100110 #
b100110 *
b100110 '
#390000
b100111 #
b100111 *
b100111 '
#400000
b101000 #
b101000 *
b101000 '
#410000
b101001 #
b101001 *
b101001 '
#420000
b101010 #
b101010 *
b101010 '
#430000
b101011 #
b101011 *
b101011 '
#440000
b101100 #
b101100 *
b101100 '
#450000
b101101 #
b101101 *
b101101 '
#460000
b101110 #
b101110 *
b101110 '
#470000
b101111 #
b101111 *
b101111 '
#480000
b110000 #
b110000 *
b110000 '
#490000
b110001 #
b110001 *
b110001 '
#500000
b110010 #
b110010 *
b110010 '
#510000
b110011 #
b110011 *
b110011 '
#520000
b110100 #
b110100 *
b110100 '
#530000
b110101 #
b110101 *
b110101 '
#540000
b110110 #
b110110 *
b110110 '
#550000
b110111 #
b110111 *
b110111 '
#560000
b111000 #
b111000 *
b111000 '
#570000
b111001 #
b111001 *
b111001 '
#580000
b111010 #
b111010 *
b111010 '
#590000
b111011 #
b111011 *
b111011 '
#600000
b111100 #
b111100 *
b111100 '
#610000
b111101 #
b111101 *
b111101 '
#620000
b111110 #
b111110 *
b111110 '
#630000
b111111 #
b111111 *
b111111 '
#640000
b1010101010101010 "
b1010101010101010 (
1$
b1000000 '
#650000
b1010101010101010 !
b1010101010101010 )
b0 #
b0 *
0$
#660000
b101010101010101 "
b101010101010101 (
b11111 %
b11111 +
1$
#670000
b101010101010101 !
b101010101010101 )
b11111 #
b11111 *
0$
#680000
b1111111111111111 "
b1111111111111111 (
b111111 %
b111111 +
1$
#690000
b1111111111111111 !
b1111111111111111 )
b111111 #
b111111 *
0$
#700000
b1000000000000 "
b1000000000000 (
b0 %
b0 +
b0 '
1$
#710000
b1000000000001 "
b1000000000001 (
b1 %
b1 +
b1 '
#720000
b1000000000010 "
b1000000000010 (
b10 %
b10 +
b10 '
#730000
b1000000000011 "
b1000000000011 (
b11 %
b11 +
b11 '
#740000
b1000000000100 "
b1000000000100 (
b100 %
b100 +
b100 '
#750000
b1000000000101 "
b1000000000101 (
b101 %
b101 +
b101 '
#760000
b1000000000110 "
b1000000000110 (
b110 %
b110 +
b110 '
#770000
b1000000000111 "
b1000000000111 (
b111 %
b111 +
b111 '
#780000
b1000000001000 "
b1000000001000 (
b1000 %
b1000 +
b1000 '
#790000
b1000000001001 "
b1000000001001 (
b1001 %
b1001 +
b1001 '
#800000
b1000000001010 "
b1000000001010 (
b1010 %
b1010 +
b1010 '
#810000
b1000000001011 "
b1000000001011 (
b1011 %
b1011 +
b1011 '
#820000
b1000000001100 "
b1000000001100 (
b1100 %
b1100 +
b1100 '
#830000
b1000000001101 "
b1000000001101 (
b1101 %
b1101 +
b1101 '
#840000
b1000000001110 "
b1000000001110 (
b1110 %
b1110 +
b1110 '
#850000
b1000000001111 "
b1000000001111 (
b1111 %
b1111 +
b1111 '
#860000
b1000000010000 "
b1000000010000 (
b10000 %
b10000 +
b10000 '
#870000
b1000000010001 "
b1000000010001 (
b10001 %
b10001 +
b10001 '
#880000
b1000000010010 "
b1000000010010 (
b10010 %
b10010 +
b10010 '
#890000
b1000000010011 "
b1000000010011 (
b10011 %
b10011 +
b10011 '
#900000
b1000000010100 "
b1000000010100 (
b10100 %
b10100 +
b10100 '
#910000
b1000000010101 "
b1000000010101 (
b10101 %
b10101 +
b10101 '
#920000
b1000000010110 "
b1000000010110 (
b10110 %
b10110 +
b10110 '
#930000
b1000000010111 "
b1000000010111 (
b10111 %
b10111 +
b10111 '
#940000
b1000000011000 "
b1000000011000 (
b11000 %
b11000 +
b11000 '
#950000
b1000000011001 "
b1000000011001 (
b11001 %
b11001 +
b11001 '
#960000
b1000000011010 "
b1000000011010 (
b11010 %
b11010 +
b11010 '
#970000
b1000000011011 "
b1000000011011 (
b11011 %
b11011 +
b11011 '
#980000
b1000000011100 "
b1000000011100 (
b11100 %
b11100 +
b11100 '
#990000
b1000000011101 "
b1000000011101 (
b11101 %
b11101 +
b11101 '
#1000000
b1000000011110 "
b1000000011110 (
b11110 %
b11110 +
b11110 '
#1010000
b1000000011111 "
b1000000011111 (
b11111 %
b11111 +
b11111 '
#1020000
b1000000100000 "
b1000000100000 (
b100000 %
b100000 +
b100000 '
#1030000
b1000000100001 "
b1000000100001 (
b100001 %
b100001 +
b100001 '
#1040000
b1000000100010 "
b1000000100010 (
b100010 %
b100010 +
b100010 '
#1050000
b1000000100011 "
b1000000100011 (
b100011 %
b100011 +
b100011 '
#1060000
b1000000100100 "
b1000000100100 (
b100100 %
b100100 +
b100100 '
#1070000
b1000000100101 "
b1000000100101 (
b100101 %
b100101 +
b100101 '
#1080000
b1000000100110 "
b1000000100110 (
b100110 %
b100110 +
b100110 '
#1090000
b1000000100111 "
b1000000100111 (
b100111 %
b100111 +
b100111 '
#1100000
b1000000101000 "
b1000000101000 (
b101000 %
b101000 +
b101000 '
#1110000
b1000000101001 "
b1000000101001 (
b101001 %
b101001 +
b101001 '
#1120000
b1000000101010 "
b1000000101010 (
b101010 %
b101010 +
b101010 '
#1130000
b1000000101011 "
b1000000101011 (
b101011 %
b101011 +
b101011 '
#1140000
b1000000101100 "
b1000000101100 (
b101100 %
b101100 +
b101100 '
#1150000
b1000000101101 "
b1000000101101 (
b101101 %
b101101 +
b101101 '
#1160000
b1000000101110 "
b1000000101110 (
b101110 %
b101110 +
b101110 '
#1170000
b1000000101111 "
b1000000101111 (
b101111 %
b101111 +
b101111 '
#1180000
b1000000110000 "
b1000000110000 (
b110000 %
b110000 +
b110000 '
#1190000
b1000000110001 "
b1000000110001 (
b110001 %
b110001 +
b110001 '
#1200000
b1000000110010 "
b1000000110010 (
b110010 %
b110010 +
b110010 '
#1210000
b1000000110011 "
b1000000110011 (
b110011 %
b110011 +
b110011 '
#1220000
b1000000110100 "
b1000000110100 (
b110100 %
b110100 +
b110100 '
#1230000
b1000000110101 "
b1000000110101 (
b110101 %
b110101 +
b110101 '
#1240000
b1000000110110 "
b1000000110110 (
b110110 %
b110110 +
b110110 '
#1250000
b1000000110111 "
b1000000110111 (
b110111 %
b110111 +
b110111 '
#1260000
b1000000111000 "
b1000000111000 (
b111000 %
b111000 +
b111000 '
#1270000
b1000000111001 "
b1000000111001 (
b111001 %
b111001 +
b111001 '
#1280000
b1000000111010 "
b1000000111010 (
b111010 %
b111010 +
b111010 '
#1290000
b1000000111011 "
b1000000111011 (
b111011 %
b111011 +
b111011 '
#1300000
b1000000111100 "
b1000000111100 (
b111100 %
b111100 +
b111100 '
#1310000
b1000000111101 "
b1000000111101 (
b111101 %
b111101 +
b111101 '
#1320000
b1000000111110 "
b1000000111110 (
b111110 %
b111110 +
b111110 '
#1330000
b1000000111111 !
b1000000111111 )
b1000000111111 "
b1000000111111 (
b111111 %
b111111 +
b111111 '
#1340000
b1000000000000 !
b1000000000000 )
b0 #
b0 *
0$
b0 '
#1350000
b1000000000001 !
b1000000000001 )
b1 #
b1 *
b1 '
#1360000
b1000000000010 !
b1000000000010 )
b10 #
b10 *
b10 '
#1370000
b1000000000011 !
b1000000000011 )
b11 #
b11 *
b11 '
#1380000
b1000000000100 !
b1000000000100 )
b100 #
b100 *
b100 '
#1390000
b1000000000101 !
b1000000000101 )
b101 #
b101 *
b101 '
#1400000
b1000000000110 !
b1000000000110 )
b110 #
b110 *
b110 '
#1410000
b1000000000111 !
b1000000000111 )
b111 #
b111 *
b111 '
#1420000
b1000000001000 !
b1000000001000 )
b1000 #
b1000 *
b1000 '
#1430000
b1000000001001 !
b1000000001001 )
b1001 #
b1001 *
b1001 '
#1440000
b1000000001010 !
b1000000001010 )
b1010 #
b1010 *
b1010 '
#1450000
b1000000001011 !
b1000000001011 )
b1011 #
b1011 *
b1011 '
#1460000
b1000000001100 !
b1000000001100 )
b1100 #
b1100 *
b1100 '
#1470000
b1000000001101 !
b1000000001101 )
b1101 #
b1101 *
b1101 '
#1480000
b1000000001110 !
b1000000001110 )
b1110 #
b1110 *
b1110 '
#1490000
b1000000001111 !
b1000000001111 )
b1111 #
b1111 *
b1111 '
#1500000
b1000000010000 !
b1000000010000 )
b10000 #
b10000 *
b10000 '
#1510000
b1000000010001 !
b1000000010001 )
b10001 #
b10001 *
b10001 '
#1520000
b1000000010010 !
b1000000010010 )
b10010 #
b10010 *
b10010 '
#1530000
b1000000010011 !
b1000000010011 )
b10011 #
b10011 *
b10011 '
#1540000
b1000000010100 !
b1000000010100 )
b10100 #
b10100 *
b10100 '
#1550000
b1000000010101 !
b1000000010101 )
b10101 #
b10101 *
b10101 '
#1560000
b1000000010110 !
b1000000010110 )
b10110 #
b10110 *
b10110 '
#1570000
b1000000010111 !
b1000000010111 )
b10111 #
b10111 *
b10111 '
#1580000
b1000000011000 !
b1000000011000 )
b11000 #
b11000 *
b11000 '
#1590000
b1000000011001 !
b1000000011001 )
b11001 #
b11001 *
b11001 '
#1600000
b1000000011010 !
b1000000011010 )
b11010 #
b11010 *
b11010 '
#1610000
b1000000011011 !
b1000000011011 )
b11011 #
b11011 *
b11011 '
#1620000
b1000000011100 !
b1000000011100 )
b11100 #
b11100 *
b11100 '
#1630000
b1000000011101 !
b1000000011101 )
b11101 #
b11101 *
b11101 '
#1640000
b1000000011110 !
b1000000011110 )
b11110 #
b11110 *
b11110 '
#1650000
b1000000011111 !
b1000000011111 )
b11111 #
b11111 *
b11111 '
#1660000
b1000000100000 !
b1000000100000 )
b100000 #
b100000 *
b100000 '
#1670000
b1000000100001 !
b1000000100001 )
b100001 #
b100001 *
b100001 '
#1680000
b1000000100010 !
b1000000100010 )
b100010 #
b100010 *
b100010 '
#1690000
b1000000100011 !
b1000000100011 )
b100011 #
b100011 *
b100011 '
#1700000
b1000000100100 !
b1000000100100 )
b100100 #
b100100 *
b100100 '
#1710000
b1000000100101 !
b1000000100101 )
b100101 #
b100101 *
b100101 '
#1720000
b1000000100110 !
b1000000100110 )
b100110 #
b100110 *
b100110 '
#1730000
b1000000100111 !
b1000000100111 )
b100111 #
b100111 *
b100111 '
#1740000
b1000000101000 !
b1000000101000 )
b101000 #
b101000 *
b101000 '
#1750000
b1000000101001 !
b1000000101001 )
b101001 #
b101001 *
b101001 '
#1760000
b1000000101010 !
b1000000101010 )
b101010 #
b101010 *
b101010 '
#1770000
b1000000101011 !
b1000000101011 )
b101011 #
b101011 *
b101011 '
#1780000
b1000000101100 !
b1000000101100 )
b101100 #
b101100 *
b101100 '
#1790000
b1000000101101 !
b1000000101101 )
b101101 #
b101101 *
b101101 '
#1800000
b1000000101110 !
b1000000101110 )
b101110 #
b101110 *
b101110 '
#1810000
b1000000101111 !
b1000000101111 )
b101111 #
b101111 *
b101111 '
#1820000
b1000000110000 !
b1000000110000 )
b110000 #
b110000 *
b110000 '
#1830000
b1000000110001 !
b1000000110001 )
b110001 #
b110001 *
b110001 '
#1840000
b1000000110010 !
b1000000110010 )
b110010 #
b110010 *
b110010 '
#1850000
b1000000110011 !
b1000000110011 )
b110011 #
b110011 *
b110011 '
#1860000
b1000000110100 !
b1000000110100 )
b110100 #
b110100 *
b110100 '
#1870000
b1000000110101 !
b1000000110101 )
b110101 #
b110101 *
b110101 '
#1880000
b1000000110110 !
b1000000110110 )
b110110 #
b110110 *
b110110 '
#1890000
b1000000110111 !
b1000000110111 )
b110111 #
b110111 *
b110111 '
#1900000
b1000000111000 !
b1000000111000 )
b111000 #
b111000 *
b111000 '
#1910000
b1000000111001 !
b1000000111001 )
b111001 #
b111001 *
b111001 '
#1920000
b1000000111010 !
b1000000111010 )
b111010 #
b111010 *
b111010 '
#1930000
b1000000111011 !
b1000000111011 )
b111011 #
b111011 *
b111011 '
#1940000
b1000000111100 !
b1000000111100 )
b111100 #
b111100 *
b111100 '
#1950000
b1000000111101 !
b1000000111101 )
b111101 #
b111101 *
b111101 '
#1960000
b1000000111110 !
b1000000111110 )
b111110 #
b111110 *
b111110 '
#1970000
b1000000111111 !
b1000000111111 )
b111111 #
b111111 *
b111111 '
#1980000
b1101111010101101 "
b1101111010101101 (
b1010 %
b1010 +
1$
b1000000 '
#1990000
b1101111010101101 !
b1101111010101101 )
b1010 #
b1010 *
0$
#2000000
b1011111011101111 !
b1011111011101111 )
b1011111011101111 "
b1011111011101111 (
1$
#2010000
0$
#2020000
b1000000010100 !
b1000000010100 )
b10100 #
b10100 *
#2030000
b1100110011001100 "
b1100110011001100 (
b10100 %
b10100 +
#2050000
b1000100010001 "
b1000100010001 (
b101 %
b101 +
1$
#2060000
b10001000100010 "
b10001000100010 (
b110010 %
b110010 +
#2070000
b11001100110011 "
b11001100110011 (
b1111 %
b1111 +
#2080000
b100010001000100 "
b100010001000100 (
b101000 %
b101000 +
#2090000
b1000100010001 !
b1000100010001 )
b101 #
b101 *
0$
#2100000
b10001000100010 !
b10001000100010 )
b110010 #
b110010 *
#2110000
b11001100110011 !
b11001100110011 )
b1111 #
b1111 *
#2120000
b100010001000100 !
b100010001000100 )
b101000 #
b101000 *
#2130000
b1010000010100000 "
b1010000010100000 (
b0 %
b0 +
1$
#2140000
b1011000010110000 "
b1011000010110000 (
b111111 %
b111111 +
#2150000
b1010000010100000 !
b1010000010100000 )
b0 #
b0 *
0$
#2160000
b1011000010110000 !
b1011000010110000 )
b111111 #
b111111 *
#2170000
b1000000011110 !
b1000000011110 )
b11110 #
b11110 *
b1001100110011001 "
b1001100110011001 (
b11001 %
b11001 +
1$
#2180000
b1001100110011001 !
b1001100110011001 )
b11001 #
b11001 *
