Code/Control_Unit/control_unit.v
// Auto-generated Verilog Control Decoder
module control_unit(
    input  [26:0] opcode_in,
    input  [3:0] break_flag,
    output [17:0] control
);

    wire [22:0] opcode = opcode_in[22:0];
    wire Y0 = opcode_in[26];
    wire Y1 = opcode_in[25];
    wire X0 = opcode_in[24];
    wire X1 = opcode_in[23];

    // One-hot opcode mapping
    localparam NOOP = 0;
    localparam INPUTC = 1;
    localparam INPUTCF = 2;
    localparam INPUTD = 3;
    localparam INPUTDF = 4;
    localparam MOVE = 5;
    localparam LOADI_LOADP = 6;
    localparam ADD = 7;
    localparam ADDI = 8;
    localparam SUB = 9;
    localparam SUBI = 10;
    localparam LOAD = 11;
    localparam LOADF = 12;
    localparam STORE = 13;
    localparam STOREF = 14;
    localparam SHIFTL = 15;
    localparam SHIFTR = 16;
    localparam CMP = 17;
    localparam JUMP = 18;
    localparam BRE_BRZ = 19;
    localparam BRNE_BRNZ = 20;
    localparam BRG = 21;
    localparam BRGE = 22;

    // Control signal equations
    assign control[0]  = opcode[INPUTC] | opcode[INPUTCF]; // IMEM_WRITE_ENABLE
    assign control[1]  = opcode[JUMP] | (opcode[BRE_BRZ] & break_flag[0]) | (opcode[BRNE_BRNZ] & break_flag[1]) | (opcode[BRG] & break_flag[2]) | (opcode[BRGE] & break_flag[3]); // PROGRAM_COUNTER_MUX
    assign control[2]  = 1'b1; // PROGRAM_WRITE_ENABLE
	 assign control[3] = ((opcode[INPUTCF] | opcode[INPUTDF] | opcode[ADD] | opcode[ADDI] | opcode[SUB] | opcode[SUBI] | opcode[SHIFTL] | opcode[SHIFTR] | opcode[CMP]) & X1) | ((opcode[MOVE] | opcode[LOADF] | opcode[STOREF]) & Y1); // REGISTERS_PORT0_SELECT1

    assign control[4] = ((opcode[INPUTCF] | opcode[INPUTDF] | opcode[ADD] | opcode[ADDI] | opcode[SUB] | opcode[SUBI] | opcode[SHIFTL] | opcode[SHIFTR] | opcode[CMP]) & X0) | ((opcode[MOVE] | opcode[LOADF] | opcode[STOREF]) & Y0); // REGISTERS_PORT0_SELECT0

    assign control[5] = ((opcode[STORE] | opcode[STOREF]) & X1) | ((opcode[ADD] | opcode[SUB] | opcode[CMP]) & Y1); // REGISTERS_PORT1_SELECT1

    assign control[6] = ((opcode[STORE] | opcode[STOREF]) & X0) | ((opcode[ADD] | opcode[SUB] | opcode[CMP]) & Y0); // REGISTERS_PORT1_SELECT0

    assign control[7] = ((opcode[MOVE] | opcode[LOADI_LOADP] | opcode[ADD] | opcode[ADDI] | opcode[SUB] | opcode[SUBI] | opcode[LOAD] | opcode[LOADF] | opcode[SHIFTL] | opcode[SHIFTR]) & X1); // REGISTERS_WRITE_SELECT1

    assign control[8] = ((opcode[MOVE] | opcode[LOADI_LOADP] | opcode[ADD] | opcode[ADDI] | opcode[SUB] | opcode[SUBI] | opcode[LOAD] | opcode[LOADF] | opcode[SHIFTL] | opcode[SHIFTR]) & X0); // REGISTERS_WRITE_SELECT0

    assign control[9]  = opcode[MOVE] | opcode[LOADI_LOADP] | opcode[ADD] | opcode[ADDI] | opcode[SUB] | opcode[SUBI] | opcode[LOAD] | opcode[LOADF] | opcode[SHIFTL] | opcode[SHIFTR]; // REGISTERS_WRITE_ENABLE
    assign control[10] = opcode[INPUTCF] | opcode[INPUTDF] | opcode[MOVE] | opcode[ADDI] | opcode[SUBI] | opcode[LOADF] | opcode[STOREF]; // ALU_SOURCE_MUX
    assign control[11] = opcode[INPUTCF] | opcode[INPUTDF] | opcode[MOVE] | opcode[ADD] | opcode[ADDI] | opcode[SUB] | opcode[SUBI] | opcode[LOADF] | opcode[STOREF] | opcode[CMP]; // ALU_SELECT1
    assign control[12] = opcode[SUB] | opcode[SUBI] | opcode[SHIFTR] | opcode[CMP]; // ALU_SELECT0
    assign control[13] = opcode[ADD] | opcode[ADDI] | opcode[SUB] | opcode[SUBI] | opcode[SHIFTL] | opcode[SHIFTR] | opcode[CMP]; // FLAGS_WRITE_ENABLE
    assign control[14] = opcode[INPUTC] | opcode[INPUTD] | opcode[LOADI_LOADP] | opcode[LOAD] | opcode[STORE]; // ALU_RESET_MUX
    assign control[15] = opcode[INPUTD] | opcode[INPUTDF]; // DMEM_INPUT_MUX
    assign control[16] = opcode[INPUTD] | opcode[INPUTDF] | opcode[STORE] | opcode[STOREF]; // DMEM_WRITE_ENABLE
    assign control[17] = opcode[LOAD] | opcode[LOADF]; // REG_WRITEBACK_MUX

endmodule

Code/Control_Unit/testbench.v
`timescale 1ns / 1ps

module testbench;

    // Inputs
    reg [26:0] opcode_in;
    reg [3:0]  break_flag;

    // Outputs
    wire [17:0] control;

    // Instantiate the DUT
    control_unit dut (
        .opcode_in(opcode_in),
        .break_flag(break_flag),
        .control(control)
    );

    // Task to display results neatly
    task display_state;
        input [26:0] opcode_in_t;
        input [3:0]  break_flag_t;
        input [17:0] control_t;
        begin
            $display("Time=%0t | opcode_in=%b | break_flag=%b | control=%b",
                     $time, opcode_in_t, break_flag_t, control_t);
        end
    endtask

    initial begin
        $dumpfile("control_unit_tb.vcd");
        $dumpvars(0, testbench);

        // Initialize inputs
        opcode_in   = 27'b0;
        break_flag  = 4'b0000;
        #10;

        // Example 1: LOADI_LOADP active (bit 6)
        opcode_in = 27'b0000000000000000000000010000000; // one-hot at position 6
        break_flag = 4'b0000;
        #10 display_state(opcode_in, break_flag, control);

        // Example 2: ADD active (bit 7)
        opcode_in = 27'b0000000000000000000000100000000;
        break_flag = 4'b0000;
        #10 display_state(opcode_in, break_flag, control);

        // Example 3: STORE active (bit 13)
        opcode_in = 27'b0000000000000100000000000000000;
        break_flag = 4'b0000;
        #10 display_state(opcode_in, break_flag, control);

        // Example 4: Branch opcodes (BRE_BRZ)
        opcode_in = 27'b0000000001000000000000000000000; // bit 19
        break_flag = 4'b1000; // B4 active
        #10 display_state(opcode_in, break_flag, control);

        // Example 5: Multiple break flags
        opcode_in = 27'b0000000010000000000000000000000; // BRNE_BRNZ
        break_flag = 4'b0100;
        #10 display_state(opcode_in, break_flag, control);

        // Example 6: BRG with B2 high
        opcode_in = 27'b0000000100000000000000000000000; // BRG
        break_flag = 4'b0010;
        #10 display_state(opcode_in, break_flag, control);

        // Example 7: BRGE with B1 high
        opcode_in = 27'b0000001000000000000000000000000; // BRGE
        break_flag = 4'b0001;
        #10 display_state(opcode_in, break_flag, control);

        // Example 8: All zeros
        opcode_in = 27'b0;
        break_flag = 4'b0000;
        #10 display_state(opcode_in, break_flag, control);

        $finish;
    end

endmodule

Code/Control_Unit/simulation/modelsim/control_unit_tb.vcd
$date
	Sat Nov 22 06:58:15 2025
$end
$version
	ModelSim Version 10.5b
$end
$timescale
	1ps
$end

$scope module testbench $end
$var reg 27 ! opcode_in [26:0] $end
$var reg 4 " break_flag [3:0] $end
$var wire 1 # control [17] $end
$var wire 1 $ control [16] $end
$var wire 1 % control [15] $end
$var wire 1 & control [14] $end
$var wire 1 ' control [13] $end
$var wire 1 ( control [12] $end
$var wire 1 ) control [11] $end
$var wire 1 * control [10] $end
$var wire 1 + control [9] $end
$var wire 1 , control [8] $end
$var wire 1 - control [7] $end
$var wire 1 . control [6] $end
$var wire 1 / control [5] $end
$var wire 1 0 control [4] $end
$var wire 1 1 control [3] $end
$var wire 1 2 control [2] $end
$var wire 1 3 control [1] $end
$var wire 1 4 control [0] $end

$scope task display_state $end
$var reg 27 5 opcode_in_t [26:0] $end
$var reg 4 6 break_flag_t [3:0] $end
$var reg 18 7 control_t [17:0] $end
$upscope $end

$scope module dut $end
$var parameter 32 8 NOOP $end
$var parameter 32 9 INPUTC $end
$var parameter 32 : INPUTCF $end
$var parameter 32 ; INPUTD $end
$var parameter 32 < INPUTDF $end
$var parameter 32 = MOVE $end
$var parameter 32 > LOADI_LOADP $end
$var parameter 32 ? ADD $end
$var parameter 32 @ ADDI $end
$var parameter 32 A SUB $end
$var parameter 32 B SUBI $end
$var parameter 32 C LOAD $end
$var parameter 32 D LOADF $end
$var parameter 32 E STORE $end
$var parameter 32 F STOREF $end
$var parameter 32 G SHIFTL $end
$var parameter 32 H SHIFTR $end
$var parameter 32 I CMP $end
$var parameter 32 J JUMP $end
$var parameter 32 K BRE_BRZ $end
$var parameter 32 L BRNE_BRNZ $end
$var parameter 32 M BRG $end
$var parameter 32 N BRGE $end
$var wire 1 O opcode_in [26] $end
$var wire 1 P opcode_in [25] $end
$var wire 1 Q opcode_in [24] $end
$var wire 1 R opcode_in [23] $end
$var wire 1 S opcode_in [22] $end
$var wire 1 T opcode_in [21] $end
$var wire 1 U opcode_in [20] $end
$var wire 1 V opcode_in [19] $end
$var wire 1 W opcode_in [18] $end
$var wire 1 X opcode_in [17] $end
$var wire 1 Y opcode_in [16] $end
$var wire 1 Z opcode_in [15] $end
$var wire 1 [ opcode_in [14] $end
$var wire 1 \ opcode_in [13] $end
$var wire 1 ] opcode_in [12] $end
$var wire 1 ^ opcode_in [11] $end
$var wire 1 _ opcode_in [10] $end
$var wire 1 ` opcode_in [9] $end
$var wire 1 a opcode_in [8] $end
$var wire 1 b opcode_in [7] $end
$var wire 1 c opcode_in [6] $end
$var wire 1 d opcode_in [5] $end
$var wire 1 e opcode_in [4] $end
$var wire 1 f opcode_in [3] $end
$var wire 1 g opcode_in [2] $end
$var wire 1 h opcode_in [1] $end
$var wire 1 i opcode_in [0] $end
$var wire 1 j break_flag [3] $end
$var wire 1 k break_flag [2] $end
$var wire 1 l break_flag [1] $end
$var wire 1 m break_flag [0] $end
$var wire 1 # control [17] $end
$var wire 1 $ control [16] $end
$var wire 1 % control [15] $end
$var wire 1 & control [14] $end
$var wire 1 ' control [13] $end
$var wire 1 ( control [12] $end
$var wire 1 ) control [11] $end
$var wire 1 * control [10] $end
$var wire 1 + control [9] $end
$var wire 1 , control [8] $end
$var wire 1 - control [7] $end
$var wire 1 . control [6] $end
$var wire 1 / control [5] $end
$var wire 1 0 control [4] $end
$var wire 1 1 control [3] $end
$var wire 1 2 control [2] $end
$var wire 1 3 control [1] $end
$var wire 1 4 control [0] $end
$var wire 1 n opcode [22] $end
$var wire 1 o opcode [21] $end
$var wire 1 p opcode [20] $end
$var wire 1 q opcode [19] $end
$var wire 1 r opcode [18] $end
$var wire 1 s opcode [17] $end
$var wire 1 t opcode [16] $end
$var wire 1 u opcode [15] $end
$var wire 1 v opcode [14] $end
$var wire 1 w opcode [13] $end
$var wire 1 x opcode [12] $end
$var wire 1 y opcode [11] $end
$var wire 1 z opcode [10] $end
$var wire 1 { opcode [9] $end
$var wire 1 | opcode [8] $end
$var wire 1 } opcode [7] $end
$var wire 1 ~ opcode [6] $end
$var wire 1 !! opcode [5] $end
$var wire 1 "! opcode [4] $end
$var wire 1 #! opcode [3] $end
$var wire 1 $! opcode [2] $end
$var wire 1 %! opcode [1] $end
$var wire 1 &! opcode [0] $end
$var wire 1 '! Y0 $end
$var wire 1 (! Y1 $end
$var wire 1 )! X0 $end
$var wire 1 *! X1 $end
$upscope $end
$upscope $end
$enddefinitions $end
#0
$dumpvars
b0 !
b0 "
bx 5
bx 6
bx 7
b0 8
b1 9
b10 :
b11 ;
b100 <
b101 =
b110 >
b111 ?
b1000 @
b1001 A
b1010 B
b1011 C
b1100 D
b1101 E
b1110 F
b1111 G
b10000 H
b10001 I
b10010 J
b10011 K
b10100 L
b10101 M
b10110 N
04
03
12
01
00
0/
0.
0-
0,
0+
0*
0)
0(
0'
0&
0%
0$
0#
0&!
0%!
0$!
0#!
0"!
0!!
0~
0}
0|
0{
0z
0y
0x
0w
0v
0u
0t
0s
0r
0q
0p
0o
0n
0'!
0(!
0)!
0*!
0m
0l
0k
0j
0i
0h
0g
0f
0e
0d
0c
0b
0a
0`
0_
0^
0]
0\
0[
0Z
0Y
0X
0W
0V
0U
0T
0S
0R
0Q
0P
0O
$end
#10000
b10000000 !
1b
1}
1'
1)
1+
#20000
b10000000 5
b0 6
b10101000000100 7
b100000000 !
0b
1a
0}
1|
1*
#30000
b100000000 5
b10111000000100 7
b100000000000000000 !
0a
1X
0|
1s
1(
0*
0+
#40000
b100000000000000000 5
b11100000000100 7
b1000000000000000000000 !
b1000 "
1j
0X
1T
0s
1o
0(
0'
0)
#50000
b1000000000000000000000 5
b1000 6
b100 7
b10000000000000000000000 !
b100 "
1k
0j
0T
1S
13
0o
1n
03
#60000
b10000000000000000000000 5
b100 6
b100000000000000000000000 !
b10 "
1l
0k
0S
1R
1*!
0n
#70000
b100000000000000000000000 5
b10 6
b1000000000000000000000000 !
b1 "
1m
0l
0R
1Q
1)!
0*!
#80000
b1000000000000000000000000 5
b1 6
b0 !
b0 "
0m
0Q
0)!
#90000
b0 5
b0 6
